{
  "id": "520d1a4f-a941-46b8-a425-c6178d9044aa",
  "timestamp": "2023-09-05T01:12:41.618Z",
  "equipment": {
    "id": "5ead3196-bcf1-4de3-9f90-64f6400370f6",
    "name": "Server",
    "createdAt": "2023-09-05T01:12:41.618Z",
    "updatedAt": "2023-09-05T01:12:41.618Z",
    "children": [
      {
        "id": "01009ec6-7b44-49ca-8360-7e8aa7b7cb5f",
        "name": "Network Card",
        "createdAt": "2023-09-05T01:12:41.618Z",
        "updatedAt": "2023-09-05T01:12:41.618Z",
        "children": [],
        "userDefinedFields": {}
      },
      {
        "id": "1c40abc1-b76a-4f61-bdec-943d680e187d",
        "name": "Network Card",
        "createdAt": "2023-09-05T01:12:41.618Z",
        "updatedAt": "2023-09-05T01:12:41.618Z",
        "children": [],
        "userDefinedFields": {}
      }
    ],
    "userDefinedFields": {}
  }
}